warframe_alerts_rss/WarframeAlert.py
warframe_alerts_rss/__init__.py
warframe_alerts_rss/warframe_alerts_rss.py
warframe_alerts_rss-0.0.1.dist-info/METADATA
warframe_alerts_rss-0.0.1.dist-info/RECORD
warframe_alerts_rss-0.0.1.dist-info/WHEEL
warframe_alerts_rss-0.0.1.dist-info/top_level.txt
