Metadata-Version: 2.1
Name: warframe-alerts-rss
Version: 0.0.1
Summary: Get Warframe Alerts From http://content.warframe.com/dynamic/rss.php
Home-page: https://github.com/hackcrafter427/warframe_alerts_rss
Author: Tong Miao (illemonati)
Author-email: tonymiaotong@tioft.tech
License: UNKNOWN
Platform: UNKNOWN
